{"is_source_file": true, "format": "JavaScript", "description": "This file provides a centralized error handling middleware function for an Express.js application, logging error details and sending standardized error responses.", "external_files": ["../config/logger"], "external_methods": ["Logger.error"], "published": ["errorHandler"], "classes": [], "methods": [{"name": "errorHandler(err, req, res, next)", "description": "Middleware function to handle errors, log details, and respond with JSON error message.", "scope": "", "scopeKind": ""}, {"name": "exports(err, req, res, next)", "scope": "module", "scopeKind": "function", "description": "unavailable"}], "calls": ["Logger.error", "res.status", "res.json", "new Date"], "search-terms": ["error handler", "middleware", "Express.js", "logger", "error logging"], "state": 2, "file_id": 18, "knowledge_revision": 39, "git_revision": "", "ctags": [{"_type": "tag", "name": "Logger", "path": "/home/kavia/workspace/code-generation/personal-notes-manager-24022-24060/notes_backend/src/middleware/error.js", "pattern": "/^const Logger = require('..\\/config\\/logger');$/", "language": "JavaScript", "kind": "constant"}, {"_type": "tag", "name": "errorHandler", "path": "/home/kavia/workspace/code-generation/personal-notes-manager-24022-24060/notes_backend/src/middleware/error.js", "pattern": "/^module.exports = function errorHandler(err, req, res, next) {$/", "language": "JavaScript", "kind": "function", "signature": "(err, req, res, next)"}, {"_type": "tag", "name": "exports", "path": "/home/kavia/workspace/code-generation/personal-notes-manager-24022-24060/notes_backend/src/middleware/error.js", "pattern": "/^module.exports = function errorHandler(err, req, res, next) {$/", "language": "JavaScript", "kind": "function", "signature": "(err, req, res, next)", "scope": "module", "scopeKind": "function"}], "hash": "1a32889e274f9d9f93af55e8ba84b010", "format-version": 4, "code-base-name": "notes_backend", "filename": "notes_backend/src/middleware/error.js", "revision_history": [{"39": ""}]}